odoo10_addon_l10n_it_fiscalcode_invoice-10.0.1.0.0-py2.7-nspkg.pth
odoo/addons/l10n_it_fiscalcode_invoice/README.rst
odoo/addons/l10n_it_fiscalcode_invoice/__init__.py
odoo/addons/l10n_it_fiscalcode_invoice/__manifest__.py
odoo/addons/l10n_it_fiscalcode_invoice/i18n/it.po
odoo/addons/l10n_it_fiscalcode_invoice/static/description/icon.png
odoo/addons/l10n_it_fiscalcode_invoice/views/report_invoice.xml
odoo10_addon_l10n_it_fiscalcode_invoice-10.0.1.0.0.dist-info/DESCRIPTION.rst
odoo10_addon_l10n_it_fiscalcode_invoice-10.0.1.0.0.dist-info/METADATA
odoo10_addon_l10n_it_fiscalcode_invoice-10.0.1.0.0.dist-info/RECORD
odoo10_addon_l10n_it_fiscalcode_invoice-10.0.1.0.0.dist-info/WHEEL
odoo10_addon_l10n_it_fiscalcode_invoice-10.0.1.0.0.dist-info/metadata.json
odoo10_addon_l10n_it_fiscalcode_invoice-10.0.1.0.0.dist-info/namespace_packages.txt
odoo10_addon_l10n_it_fiscalcode_invoice-10.0.1.0.0.dist-info/top_level.txt
